protector/__init__.py
protector/admin.py
protector/admin_forms.py
protector/apps.py
protector/backends.py
protector/exceptions.py
protector/helpers.py
protector/internals.py
protector/managers.py
protector/models.py
protector/query.py
protector/querysets.py
protector/reserved_reasons.py
protector/tests.py
protector/locale/ru/LC_MESSAGES/django.mo
protector/locale/ru/LC_MESSAGES/django.po
protector/migrations/0001_initial.py
protector/migrations/0002_auto_20160607_0827.py
protector/migrations/0003_auto_20160607_0838.py
protector/migrations/0004_auto_20170906_1215.py
protector/migrations/0005_auto_20180725_1629.py
protector/migrations/0006_auto_20180726_1229.py
protector/migrations/0007_auto_20190604_1837.py
protector/migrations/0008_auto_20191128_1246.py
protector/migrations/0009_auto_20210302_1013.py
protector/migrations/0010_auto_20210302_1030.py
protector/migrations/0011_auto_20210302_1031.py
protector/migrations/0012_alter_genericusertogroup_responsible_and_more.py
protector/migrations/0013_auto_20241009_1252.py
protector/migrations/__init__.py
protector/migrations/__pycache__/0001_initial.cpython-310.pyc
protector/migrations/__pycache__/0002_auto_20160607_0827.cpython-310.pyc
protector/migrations/__pycache__/0003_auto_20160607_0838.cpython-310.pyc
protector/migrations/__pycache__/0004_auto_20170906_1215.cpython-310.pyc
protector/migrations/__pycache__/0005_auto_20180725_1629.cpython-310.pyc
protector/migrations/__pycache__/0006_auto_20180726_1229.cpython-310.pyc
protector/migrations/__pycache__/0007_auto_20190604_1837.cpython-310.pyc
protector/migrations/__pycache__/0008_auto_20191128_1246.cpython-310.pyc
protector/migrations/__pycache__/0009_auto_20210302_1013.cpython-310.pyc
protector/migrations/__pycache__/0010_auto_20210302_1030.cpython-310.pyc
protector/migrations/__pycache__/0011_auto_20210302_1031.cpython-310.pyc
protector/migrations/__pycache__/0012_alter_genericusertogroup_responsible_and_more.cpython-310.pyc
django_protector-0.7.3.dist-info/LICENSE
django_protector-0.7.3.dist-info/METADATA
django_protector-0.7.3.dist-info/WHEEL
django_protector-0.7.3.dist-info/top_level.txt
django_protector-0.7.3.dist-info/RECORD
