Metadata-Version: 2.1
Name: django-protector
Version: 0.7.3
Summary: Django application for managing object level permissions and generic groups
Home-page: https://github.com/grey0ne/django-protector
Author: Sergey Lihobabin
Author-email: greyone@greyone.ru
License: MIT License
Classifier: Environment :: Web Environment
Classifier: Framework :: Django
Classifier: Intended Audience :: Developers
Classifier: License :: OSI Approved :: MIT License
Classifier: Operating System :: OS Independent
Classifier: Programming Language :: Python
Classifier: Programming Language :: Python :: 3
Classifier: Topic :: Internet :: WWW/HTTP
Classifier: Topic :: Internet :: WWW/HTTP :: Dynamic Content
License-File: LICENSE
Requires-Dist: django-mptt>=0.11
Requires-Dist: Django>=4.0
Requires-Dist: future>=0.16.0
